harborapi/__about__.py
harborapi/__init__.py
harborapi/_types.py
harborapi/auth.py
harborapi/client.py
harborapi/client_sync.py
harborapi/exceptions.py
harborapi/log.py
harborapi/py.typed
harborapi/responselog.py
harborapi/retry.py
harborapi/utils.py
harborapi/version.py
harborapi/ext/__init__.py
harborapi/ext/api.py
harborapi/ext/artifact.py
harborapi/ext/cve.py
harborapi/ext/regex.py
harborapi/ext/report.py
harborapi/ext/stats.py
harborapi/models/__init__.py
harborapi/models/_models.py
harborapi/models/_scanner.py
harborapi/models/base.py
harborapi/models/buildhistory.py
harborapi/models/file.py
harborapi/models/mappings.py
harborapi/models/models.py
harborapi/models/oidc.py
harborapi/models/scanner.py
harborapi-0.26.1.dist-info/METADATA
harborapi-0.26.1.dist-info/WHEEL
harborapi-0.26.1.dist-info/licenses/LICENSE
harborapi-0.26.1.dist-info/RECORD
