Metadata-Version: 2.3
Name: harborapi
Version: 0.26.1
Summary: Async Harbor API v2.0 client
Project-URL: Source, https://github.com/unioslo/harborapi
Project-URL: Documentation, https://unioslo.github.io/harborapi/
Project-URL: Changelog, https://github.com/unioslo/harborapi/blob/main/CHANGELOG.md
Project-URL: Issues, https://github.com/unioslo/harborapi/issues
Author-email: pederhan <pederhan@uio.no>
License: MIT
Classifier: Development Status :: 4 - Beta
Classifier: Intended Audience :: Developers
Classifier: Intended Audience :: System Administrators
Classifier: License :: OSI Approved :: MIT License
Classifier: Natural Language :: English
Classifier: Operating System :: OS Independent
Classifier: Programming Language :: Python
Classifier: Programming Language :: Python :: 3.8
Classifier: Programming Language :: Python :: 3.9
Classifier: Programming Language :: Python :: 3.10
Classifier: Programming Language :: Python :: 3.11
Classifier: Programming Language :: Python :: 3.12
Classifier: Programming Language :: Python :: Implementation :: CPython
Classifier: Topic :: Internet
Classifier: Topic :: Software Development :: Libraries
Classifier: Topic :: Software Development :: Libraries :: Python Modules
Classifier: Typing :: Typed
Requires-Python: >=3.8
Requires-Dist: backoff>=2.1.2
Requires-Dist: httpx>=0.22.0
Requires-Dist: pydantic>=2.2.1
Requires-Dist: typing-extensions>=4.4.0
Provides-Extra: rich
Requires-Dist: rich>=12.6.0; extra == 'rich'
